{
  "supportive": [
    "This is actually a solid point. Well said.",
    "Agreed — someone needed to say it.",
    "I've been thinking the same thing for weeks.",
    "Respect for actually putting this out there.",
    "This tracks with what I've been hearing around town.",
    "Finally, someone with sense. Bookmarked.",
    "Clear thinking. Wish more people posted like this.",
    "Yeah this checks out. Quality take.",
    "I forwarded this to three people already.",
    "Good insight. The kind of thing you don't see enough on here.",
    "Signed. Cosigned. Notarized.",
    "This deserves more upvotes than it's getting.",
    "Couldn't have said it better. Carry on.",
    "Solid contribution to the thread. Rare.",
    "The break room needs to see this.",
    "Thank you — someone had to articulate this properly."
  ],
  "neutral": [
    "Hmm. Fair enough, I suppose.",
    "Not sure I agree but it's a take.",
    "Interesting. I'll think about it.",
    "Noted. Moving on.",
    "Okay. Sure. Why not.",
    "I see where you're going with this.",
    "That's one way to look at it.",
    "Can't argue with the logic, even if I wanted to.",
    "Filed under 'things I'll revisit later'.",
    "Reasonable. Not earth-shattering, but reasonable.",
    "This is fine. Just fine.",
    "I neither endorse nor condemn this opinion.",
    "Acknowledged. My feelings are complex.",
    "Could go either way. Time will tell.",
    "Okay I read it twice. Still processing.",
    "The data could support this. Or not."
  ],
  "cold": [
    "Not sure you've thought this through entirely.",
    "This reads like it was written in a hurry.",
    "I mean… it's a take, I guess.",
    "Are we just posting anything now?",
    "I've heard better versions of this exact opinion.",
    "This needed another draft before publishing.",
    "Respectfully: no.",
    "Bold of you to post this without sources.",
    "The confidence here is… admirable, at least.",
    "I'll pretend I didn't see this one.",
    "Someone's going to regret this post later.",
    "Tell me you're new here without telling me.",
    "I don't have the energy to explain what's wrong with this.",
    "Citation needed. Multiple citations, actually.",
    "This opinion has the structural integrity of wet cardboard.",
    "You lost me at the first sentence."
  ],
  "hostile": [
    "Absolutely not. Delete this.",
    "This is exactly what's wrong with public forums.",
    "I regret having eyes today.",
    "Tell your uncle this isn't the take he thinks it is.",
    "Reported for crimes against reasonable discourse.",
    "The audacity of posting this on a weekday.",
    "I'm going to pretend this thread doesn't exist.",
    "You could not be more wrong if you tried.",
    "This take is so bad it might loop back around to art.",
    "I'm blocking this opinion from my memory.",
    "My blood pressure spiked reading this.",
    "File this under 'reasons I avoid the internet'.",
    "The sheer wrongness is almost impressive.",
    "Do you proofread or just hit post and pray?",
    "I need to go touch grass after reading this.",
    "This opinion should require a permit."
  ],
  "pedantic_low_acumen": [
    "That's not quite how that works, actually.",
    "I think there's a fundamental misunderstanding here.",
    "This would make more sense if you'd read the fine print.",
    "Might want to double-check those numbers before posting.",
    "Common mistake — the reality is more nuanced.",
    "Tell me you skipped the documentation without telling me.",
    "Close, but not close enough to be useful.",
    "The spirit is there but the execution needs work.",
    "This is what happens when you skip the tutorial.",
    "I see what you were going for. You didn't get there.",
    "Maybe run this by someone before posting next time.",
    "The enthusiasm is noted. The accuracy is not.",
    "This reads like someone described it to you secondhand.",
    "If you're going to have an opinion, at least have the right one.",
    "Might want to sit this topic out until you've caught up.",
    "The confidence-to-competence ratio here is… notable."
  ],
  "handles": [
    "ThreadPatrol2K",
    "ManagementMaterial",
    "LedgerGhost",
    "ParkingLotPhilosopher",
    "SSA_WaitingRoom",
    "ComplianceCasual",
    "NightShiftNarrator",
    "WahooSearchRefugee",
    "RapidGateVeteran",
    "MidtownMemos",
    "MandateObserver",
    "ForumLurkerPrime",
    "IntranetEscapee",
    "BreakRoomScholar",
    "CubicleMinister",
    "DowntownDossier"
  ]
}
